coyote/__init__.py
coyote/card.py
coyote/game.py
coyote_ai_competition-1.0.0.dist-info/METADATA
coyote_ai_competition-1.0.0.dist-info/WHEEL
coyote_ai_competition-1.0.0.dist-info/top_level.txt
coyote_ai_competition-1.0.0.dist-info/RECORD
