Metadata-Version: 2.4
Name: coyote-AI-competition
Version: 1.0.0
Summary: coyote AI competition用のゲームロジックです
Author: coyote-AI-competition
Author-email: aigamecompetionorg@gmail.com
Classifier: Development Status :: 4 - Beta
Classifier: Intended Audience :: Science/Research
Classifier: Topic :: Education
Classifier: License :: OSI Approved
Classifier: Programming Language :: Python :: 3.12
Requires-Python: >=3.12
